geonames_place/__init__.py
geonames_place/admin.py
geonames_place/apps.py
geonames_place/models.py
geonames_place/serializers.py
geonames_place/urls.py
geonames_place/views.py
geonames_place/widgets.py
geonames_place/migrations/0001_initial.py
geonames_place/migrations/0002_alter_field_geonames_id_on_place.py
geonames_place/migrations/0003_place_update_from_geonames.py
geonames_place/migrations/0004_change_meta_options_on_country.py
geonames_place/migrations/__init__.py
geonames_place/static/css/geonames_place.css
geonames_place/static/js/geonames_place.js
geonames_place/templates/geonames_place/base.html
django_geonames_place-0.7.0.dist-info/AUTHORS.rst
django_geonames_place-0.7.0.dist-info/LICENSE
django_geonames_place-0.7.0.dist-info/METADATA
django_geonames_place-0.7.0.dist-info/WHEEL
django_geonames_place-0.7.0.dist-info/top_level.txt
django_geonames_place-0.7.0.dist-info/RECORD
