Metadata-Version: 2.1
Name: django-geonames-place
Version: 0.7.0
Summary: Application to access Geonames Places directly from Django.
Home-page: https://github.com/kingsdigitallab/django-geonames-place
Author: Miguel Vieira
Author-email: jmvieira@gmail.com
License: MIT
Keywords: django-geonames-place
Platform: UNKNOWN
Classifier: Development Status :: 3 - Alpha
Classifier: Framework :: Django :: 2.0
Classifier: Intended Audience :: Developers
Classifier: License :: OSI Approved :: BSD License
Classifier: Natural Language :: English
Classifier: Programming Language :: Python :: 3
Classifier: Programming Language :: Python :: 3.5
Classifier: Programming Language :: Python :: 3.6
Requires-Dist: django-model-utils (>=2.0)
Requires-Dist: geocoder
